config/__init__.py
config/conf.yaml
config/config.py
interfaces/__init__.py
interfaces/a2l/__init__.py
interfaces/a2l/a2l.py
interfaces/adb/adb.py
interfaces/canoe/N3_E3U1_XCD.cfg
interfaces/canoe/canoe.py
interfaces/demo_interfaces/__init__.py
interfaces/demo_interfaces/can_interface.py
interfaces/demo_interfaces/message_interface.py
interfaces/demo_interfaces/rest_interface.py
interfaces/demo_interfaces/serial_interface.py
interfaces/demo_interfaces/test_demo_interfaces.py
interfaces/hex/__init__.py
interfaces/hex/srec19.py
interfaces/inca/Etas.Base.ComSupport.dll
interfaces/inca/cebra.ini
interfaces/inca/inca.py
interfaces/inca/incacom.dll
interfaces/inca/incacom.tlb
interfaces/mi_ant/mi_ant.py
interfaces/mi_ant/mi_ant_lib.py
interfaces/socketio/client.py
interfaces/socketio/server.py
interfaces/tsmaster/tsmaster.py
interfaces/tsp/tsp.py
interfaces/tsp/tsp_request.py
interfaces/veristand/veristand.py
pyecutest/__init__.py
pyecutest/cli.py
pyecutest-0.1.0.dist-info/METADATA
pyecutest-0.1.0.dist-info/WHEEL
pyecutest-0.1.0.dist-info/dependency_links.txt
pyecutest-0.1.0.dist-info/entry_points.txt
pyecutest-0.1.0.dist-info/top_level.txt
pyecutest-0.1.0.dist-info/RECORD
