Metadata-Version: 2.4
Name: pyecutest
Version: 0.1.0
Summary: A testing framework for ECU testing based on pytest
Home-page: https://github.com/yourusername/pyecutest
Author: PyECUTest Team
Author-email: your.email@example.com
Classifier: Programming Language :: Python :: 3
Classifier: License :: OSI Approved :: MIT License
Classifier: Operating System :: OS Independent
Requires-Python: >=3.10
Requires-Dist: pytest>=7.0.0
Requires-Dist: allure-pytest>=2.13.0
Requires-Dist: cantools>=40.0.0
Requires-Dist: python-can>=4.5.0
Requires-Dist: niveristand>=3.2.0
Requires-Dist: adbutils>=2.8.0
Requires-Dist: pya2l>=0.1.4
Requires-Dist: py_canoe>=3.0.2
Requires-Dist: pymysql>=1.1.1
Requires-Dist: uiautomator2>=3.2.2
Requires-Dist: requests>=2.28.0
Requires-Dist: pythonnet>=3.0.4
Requires-Dist: watchdog>=5.0.3
Requires-Dist: pyyaml>=6.0.2
Requires-Dist: pandas>=1.5.0
Requires-Dist: openpyxl>=3.0.0
Requires-Dist: pytest-assume>=2.4.3
Requires-Dist: pytest-csv>=3.0.0
Requires-Dist: psutil>=6.1.0
Requires-Dist: pytest-repeat>=0.9.3
Requires-Dist: intelhex>=2.3.0
Requires-Dist: pyecharts>=2.0.7
Requires-Dist: pytest-sugar>=1.0.0
Requires-Dist: pywin32>=308
Requires-Dist: a2lparser<1.0.0,>=0.1.0
Provides-Extra: a2l
Requires-Dist: a2lparser<1.0.0,>=0.1.0; extra == "a2l"
Dynamic: author
Dynamic: author-email
Dynamic: classifier
Dynamic: description
Dynamic: description-content-type
Dynamic: home-page
Dynamic: provides-extra
Dynamic: requires-dist
Dynamic: requires-python
Dynamic: summary
